static_data_functions_importer/__init__.py
static_data_functions_importer/importer.py
static_data_functions_importer-1.0.0.dist-info/METADATA
static_data_functions_importer-1.0.0.dist-info/WHEEL
static_data_functions_importer-1.0.0.dist-info/top_level.txt
static_data_functions_importer-1.0.0.dist-info/RECORD
