Metadata-Version: 2.1
Name: static_data_functions_importer
Version: 1.0.0
Author-email: J J <jai.jalah@krakenflex.com>
Requires-Python: >=3.9
Requires-Dist: sys
